[
  { "id": 1, "icon": "mail", "link": "mailto:hartaithan@gmail.com" },
  { "id": 2, "icon": "github", "link": "//github.com/Hartaithan" },
  {
    "id": 3,
    "icon": "linkedIn",
    "link": "//www.linkedin.com/in/vladimir-stepanov-605b93222/"
  },
  {
    "id": 4,
    "icon": "telegram",
    "link": "//t.me/hartaithan"
  },
  {
    "id": 5,
    "icon": "hh",
    "link": "//hh.ru/resume/c2d8f9a5ff0959ecb30039ed1f6f7933457473"
  },
  {
    "id": 6,
    "icon": "googlePlay",
    "link": "//play.google.com/store/apps/dev?id=4716065440707220964"
  }
]
